country_database/__init__.py
country_database/__version__.py
country_database/core.py
country_database/database/LICENSE
country_database/database/README.md
country_database/database/codes.tsv
country_database/database/name/en.tsv
country_database/database/name/zh.tsv
country_database/dataloader.py
country_database/generated.py
country_database/generics.py
country_database/property.py
country_database-0.1.0.dist-info/WHEEL
country_database-0.1.0.dist-info/METADATA
country_database-0.1.0.dist-info/license_files/LICENSE
country_database-0.1.0.dist-info/RECORD
