Metadata-Version: 2.1
Name: country-database
Version: 0.1.0
Summary: Country information database. Including names, capitals, currencies, etc.
License: MIT
Keywords: countries
Author-email: Ggicci <ggicci.t@gmail.com>
Requires-Python: >=3.7
Project-URL: Bug Tracker, https://github.com/ggicci/python-countries/issues
Project-URL: Homepage, https://github.com/ggicci/python-countries
Project-URL: Repository, https://github.com/ggicci/python-countries
